{"action":{"identity":{"address":"N\u0000sourcecred\u0000core\u0000IDENTITY\u000021xpEXn9bc0V8jx7bTVuAg\u0000","aliases":[],"id":"21xpEXn9bc0V8jx7bTVuAg","name":"d11","subtype":"USER"},"type":"CREATE_IDENTITY"},"ledgerTimestamp":1671499013220,"uuid":"ImXntKBtNxBugBEbVMn8MA","version":"1"}
{"action":{"alias":{"address":"N\u0000sourcecred\u0000discourse\u0000user\u0000https://sourcecred-test.discourse.group\u0000d11\u0000","description":"discourse/[@d11](https://sourcecred-test.discourse.group/u/d11/)"},"identityId":"21xpEXn9bc0V8jx7bTVuAg","type":"ADD_ALIAS"},"ledgerTimestamp":1671499013222,"uuid":"KxfJkUvz0feNhrlFyK3Maw","version":"1"}
{"action":{"identity":{"address":"N\u0000sourcecred\u0000core\u0000IDENTITY\u0000IbjSWgGA0F4Qx6Bo9u05YA\u0000","aliases":[],"id":"IbjSWgGA0F4Qx6Bo9u05YA","name":"dl-proto","subtype":"USER"},"type":"CREATE_IDENTITY"},"ledgerTimestamp":1671499013222,"uuid":"oJZlOBefzeGU2JzmHQXTrw","version":"1"}
{"action":{"alias":{"address":"N\u0000sourcecred\u0000discourse\u0000user\u0000https://sourcecred-test.discourse.group\u0000dl-proto\u0000","description":"discourse/[@dl-proto](https://sourcecred-test.discourse.group/u/dl-proto/)"},"identityId":"IbjSWgGA0F4Qx6Bo9u05YA","type":"ADD_ALIAS"},"ledgerTimestamp":1671499013223,"uuid":"bAFWukrFkTQlWU8kqpXIGg","version":"1"}
{"action":{"identity":{"address":"N\u0000sourcecred\u0000core\u0000IDENTITY\u0000ngqwrKOnZ5XnB5Xw8vm7Dg\u0000","aliases":[],"id":"ngqwrKOnZ5XnB5Xw8vm7Dg","name":"system","subtype":"BOT"},"type":"CREATE_IDENTITY"},"ledgerTimestamp":1671499013223,"uuid":"ovwBt5BHeWVAYDqW2XMYKg","version":"1"}
{"action":{"alias":{"address":"N\u0000sourcecred\u0000discourse\u0000user\u0000https://sourcecred-test.discourse.group\u0000system\u0000","description":"discourse/[@system](https://sourcecred-test.discourse.group/u/system/)"},"identityId":"ngqwrKOnZ5XnB5Xw8vm7Dg","type":"ADD_ALIAS"},"ledgerTimestamp":1671499013224,"uuid":"6qFmvZRmkvZbVsMsjqz1FQ","version":"1"}
{"action":{"identity":{"address":"N\u0000sourcecred\u0000core\u0000IDENTITY\u0000hvZIwFVu8FL9dhvDks17Sg\u0000","aliases":[],"id":"hvZIwFVu8FL9dhvDks17Sg","name":"beanow-sc-test","subtype":"USER"},"type":"CREATE_IDENTITY"},"ledgerTimestamp":1671499013224,"uuid":"jF8Q8x2GkgmPLgjDxqUaKg","version":"1"}
{"action":{"alias":{"address":"N\u0000sourcecred\u0000discourse\u0000user\u0000https://sourcecred-test.discourse.group\u0000beanow.sc-test\u0000","description":"discourse/[@beanow.sc-test](https://sourcecred-test.discourse.group/u/beanow.sc-test/)"},"identityId":"hvZIwFVu8FL9dhvDks17Sg","type":"ADD_ALIAS"},"ledgerTimestamp":1671499013224,"uuid":"Js9wev0yR8XSWqGRUeM3ew","version":"1"}
{"action":{"identity":{"address":"N\u0000sourcecred\u0000core\u0000IDENTITY\u0000do4gZ9SKRDxc7VlDgaW3EA\u0000","aliases":[],"id":"do4gZ9SKRDxc7VlDgaW3EA","name":"SourceCred","subtype":"PROJECT"},"type":"CREATE_IDENTITY"},"ledgerTimestamp":1671499013290,"uuid":"6RVWQgnaI7RKeBfpNPdNsg","version":"1"}
{"action":{"identityId":"do4gZ9SKRDxc7VlDgaW3EA","type":"TOGGLE_ACTIVATION"},"ledgerTimestamp":1671499013290,"uuid":"jNYIVuW0MHBINlUqXY77aA","version":"1"}
