{"action":{"identity":{"address":"N\u0000sourcecred\u0000core\u0000IDENTITY\u0000GyxaZDyswcm7yvhyfeHBIQ\u0000","aliases":[],"id":"GyxaZDyswcm7yvhyfeHBIQ","name":"d11","subtype":"USER"},"type":"CREATE_IDENTITY"},"ledgerTimestamp":1688862263130,"uuid":"mTmEWGix9yJREOB6QbErJg","version":"1"}
{"action":{"alias":{"address":"N\u0000sourcecred\u0000discourse\u0000user\u0000https://sourcecred-test.discourse.group\u0000d11\u0000","description":"discourse/[@d11](https://sourcecred-test.discourse.group/u/d11/)"},"identityId":"GyxaZDyswcm7yvhyfeHBIQ","type":"ADD_ALIAS"},"ledgerTimestamp":1688862263131,"uuid":"HX2vELs3765NGe4ZYxJznw","version":"1"}
{"action":{"identity":{"address":"N\u0000sourcecred\u0000core\u0000IDENTITY\u0000VokZ1WmP9DmyAxLniMHVWA\u0000","aliases":[],"id":"VokZ1WmP9DmyAxLniMHVWA","name":"dl-proto","subtype":"USER"},"type":"CREATE_IDENTITY"},"ledgerTimestamp":1688862263131,"uuid":"hM6B0wlMYNW1Y6OP1yU7eQ","version":"1"}
{"action":{"alias":{"address":"N\u0000sourcecred\u0000discourse\u0000user\u0000https://sourcecred-test.discourse.group\u0000dl-proto\u0000","description":"discourse/[@dl-proto](https://sourcecred-test.discourse.group/u/dl-proto/)"},"identityId":"VokZ1WmP9DmyAxLniMHVWA","type":"ADD_ALIAS"},"ledgerTimestamp":1688862263132,"uuid":"9Xof1U553g18rELXNL7vsw","version":"1"}
{"action":{"identity":{"address":"N\u0000sourcecred\u0000core\u0000IDENTITY\u0000gT7gXu4GyZTByRQ1c7mBaQ\u0000","aliases":[],"id":"gT7gXu4GyZTByRQ1c7mBaQ","name":"system","subtype":"BOT"},"type":"CREATE_IDENTITY"},"ledgerTimestamp":1688862263132,"uuid":"L9lpC6TOvqhPWuj9Enn5ow","version":"1"}
{"action":{"alias":{"address":"N\u0000sourcecred\u0000discourse\u0000user\u0000https://sourcecred-test.discourse.group\u0000system\u0000","description":"discourse/[@system](https://sourcecred-test.discourse.group/u/system/)"},"identityId":"gT7gXu4GyZTByRQ1c7mBaQ","type":"ADD_ALIAS"},"ledgerTimestamp":1688862263133,"uuid":"8knl9DK6iGmhmy8eLAI1QQ","version":"1"}
{"action":{"identity":{"address":"N\u0000sourcecred\u0000core\u0000IDENTITY\u000058x1Q33oAnBprH1DrqIoEw\u0000","aliases":[],"id":"58x1Q33oAnBprH1DrqIoEw","name":"beanow-sc-test","subtype":"USER"},"type":"CREATE_IDENTITY"},"ledgerTimestamp":1688862263134,"uuid":"5Gwuq4lWzkVIjpem2kzMhw","version":"1"}
{"action":{"alias":{"address":"N\u0000sourcecred\u0000discourse\u0000user\u0000https://sourcecred-test.discourse.group\u0000beanow.sc-test\u0000","description":"discourse/[@beanow.sc-test](https://sourcecred-test.discourse.group/u/beanow.sc-test/)"},"identityId":"58x1Q33oAnBprH1DrqIoEw","type":"ADD_ALIAS"},"ledgerTimestamp":1688862263134,"uuid":"UEEvT3lLYc0B6cdjIdZYag","version":"1"}
{"action":{"identity":{"address":"N\u0000sourcecred\u0000core\u0000IDENTITY\u0000gK7QZJrrpVqDO1iz5J3IVw\u0000","aliases":[],"id":"gK7QZJrrpVqDO1iz5J3IVw","name":"SourceCred","subtype":"PROJECT"},"type":"CREATE_IDENTITY"},"ledgerTimestamp":1688862263206,"uuid":"vqbE1RqMBt3PNF7NxkfEVw","version":"1"}
{"action":{"identityId":"gK7QZJrrpVqDO1iz5J3IVw","type":"TOGGLE_ACTIVATION"},"ledgerTimestamp":1688862263206,"uuid":"g88ww4k2HMpuOHreEtbIZw","version":"1"}
