{"action":{"identity":{"address":"N\u0000sourcecred\u0000core\u0000IDENTITY\u0000n1ZkWMRsqfMoLE0ty3DADA\u0000","aliases":[],"id":"n1ZkWMRsqfMoLE0ty3DADA","name":"d11","subtype":"USER"},"type":"CREATE_IDENTITY"},"ledgerTimestamp":1705969085642,"uuid":"jnvrOWJl40AiGAg9iXexOw","version":"1"}
{"action":{"alias":{"address":"N\u0000sourcecred\u0000discourse\u0000user\u0000https://sourcecred-test.discourse.group\u0000d11\u0000","description":"discourse/[@d11](https://sourcecred-test.discourse.group/u/d11/)"},"identityId":"n1ZkWMRsqfMoLE0ty3DADA","type":"ADD_ALIAS"},"ledgerTimestamp":1705969085643,"uuid":"VXoeW0nu7Jd6tKN55ElIKw","version":"1"}
{"action":{"identity":{"address":"N\u0000sourcecred\u0000core\u0000IDENTITY\u0000JYbtw86KVwmfDNbjzIr8Hg\u0000","aliases":[],"id":"JYbtw86KVwmfDNbjzIr8Hg","name":"dl-proto","subtype":"USER"},"type":"CREATE_IDENTITY"},"ledgerTimestamp":1705969085643,"uuid":"roNZyMGQ8q5H936dKQqlxg","version":"1"}
{"action":{"alias":{"address":"N\u0000sourcecred\u0000discourse\u0000user\u0000https://sourcecred-test.discourse.group\u0000dl-proto\u0000","description":"discourse/[@dl-proto](https://sourcecred-test.discourse.group/u/dl-proto/)"},"identityId":"JYbtw86KVwmfDNbjzIr8Hg","type":"ADD_ALIAS"},"ledgerTimestamp":1705969085644,"uuid":"5eqIWDMIYGn9N5IXGiBlnw","version":"1"}
{"action":{"identity":{"address":"N\u0000sourcecred\u0000core\u0000IDENTITY\u0000KOrbNt1l0qVsb2sDO8E8iA\u0000","aliases":[],"id":"KOrbNt1l0qVsb2sDO8E8iA","name":"system","subtype":"BOT"},"type":"CREATE_IDENTITY"},"ledgerTimestamp":1705969085645,"uuid":"nsrtntd9dV0OT5bZwEfmBg","version":"1"}
{"action":{"alias":{"address":"N\u0000sourcecred\u0000discourse\u0000user\u0000https://sourcecred-test.discourse.group\u0000system\u0000","description":"discourse/[@system](https://sourcecred-test.discourse.group/u/system/)"},"identityId":"KOrbNt1l0qVsb2sDO8E8iA","type":"ADD_ALIAS"},"ledgerTimestamp":1705969085645,"uuid":"MXrhnp0VkspDoBHl25Umjg","version":"1"}
{"action":{"identity":{"address":"N\u0000sourcecred\u0000core\u0000IDENTITY\u00006mhDV6dF7JJmyjsm0z3euA\u0000","aliases":[],"id":"6mhDV6dF7JJmyjsm0z3euA","name":"beanow-sc-test","subtype":"USER"},"type":"CREATE_IDENTITY"},"ledgerTimestamp":1705969085646,"uuid":"z18O3upqWPmeXwWJYqS7LA","version":"1"}
{"action":{"alias":{"address":"N\u0000sourcecred\u0000discourse\u0000user\u0000https://sourcecred-test.discourse.group\u0000beanow.sc-test\u0000","description":"discourse/[@beanow.sc-test](https://sourcecred-test.discourse.group/u/beanow.sc-test/)"},"identityId":"6mhDV6dF7JJmyjsm0z3euA","type":"ADD_ALIAS"},"ledgerTimestamp":1705969085646,"uuid":"v3f6kY5cwAtXRofqGA4N6w","version":"1"}
{"action":{"identity":{"address":"N\u0000sourcecred\u0000core\u0000IDENTITY\u0000kOGzqg5QrkgOSXy60UJijQ\u0000","aliases":[],"id":"kOGzqg5QrkgOSXy60UJijQ","name":"SourceCred","subtype":"PROJECT"},"type":"CREATE_IDENTITY"},"ledgerTimestamp":1705969085696,"uuid":"WGsvv93AC4NCZdJ4f3o0ZQ","version":"1"}
{"action":{"identityId":"kOGzqg5QrkgOSXy60UJijQ","type":"TOGGLE_ACTIVATION"},"ledgerTimestamp":1705969085697,"uuid":"y68GYZztB0eIM0rKPIp0rA","version":"1"}
