{"action":{"identity":{"address":"N\u0000sourcecred\u0000core\u0000IDENTITY\u0000uNnCwBAG0D65iw1CV5eubA\u0000","aliases":[],"id":"uNnCwBAG0D65iw1CV5eubA","name":"d11","subtype":"USER"},"type":"CREATE_IDENTITY"},"ledgerTimestamp":1704154647777,"uuid":"81Uyr44n5sRCxxV7GJwDxA","version":"1"}
{"action":{"alias":{"address":"N\u0000sourcecred\u0000discourse\u0000user\u0000https://sourcecred-test.discourse.group\u0000d11\u0000","description":"discourse/[@d11](https://sourcecred-test.discourse.group/u/d11/)"},"identityId":"uNnCwBAG0D65iw1CV5eubA","type":"ADD_ALIAS"},"ledgerTimestamp":1704154647778,"uuid":"3F7xWkq59vvg57v8sGSWKA","version":"1"}
{"action":{"identity":{"address":"N\u0000sourcecred\u0000core\u0000IDENTITY\u0000pXxtomogtlQSaSMrLln6EQ\u0000","aliases":[],"id":"pXxtomogtlQSaSMrLln6EQ","name":"dl-proto","subtype":"USER"},"type":"CREATE_IDENTITY"},"ledgerTimestamp":1704154647779,"uuid":"i4T07e5nsYWfjzDPqvK9CA","version":"1"}
{"action":{"alias":{"address":"N\u0000sourcecred\u0000discourse\u0000user\u0000https://sourcecred-test.discourse.group\u0000dl-proto\u0000","description":"discourse/[@dl-proto](https://sourcecred-test.discourse.group/u/dl-proto/)"},"identityId":"pXxtomogtlQSaSMrLln6EQ","type":"ADD_ALIAS"},"ledgerTimestamp":1704154647780,"uuid":"1xCE7EAnaPEGTDIz5bdRaA","version":"1"}
{"action":{"identity":{"address":"N\u0000sourcecred\u0000core\u0000IDENTITY\u0000SxOycQ6R3Be46nkxDlxQdw\u0000","aliases":[],"id":"SxOycQ6R3Be46nkxDlxQdw","name":"system","subtype":"BOT"},"type":"CREATE_IDENTITY"},"ledgerTimestamp":1704154647780,"uuid":"0DW5Qgg1xw7y5bx61VyFkg","version":"1"}
{"action":{"alias":{"address":"N\u0000sourcecred\u0000discourse\u0000user\u0000https://sourcecred-test.discourse.group\u0000system\u0000","description":"discourse/[@system](https://sourcecred-test.discourse.group/u/system/)"},"identityId":"SxOycQ6R3Be46nkxDlxQdw","type":"ADD_ALIAS"},"ledgerTimestamp":1704154647780,"uuid":"mzANZG48dQxK4nWoMS7YMQ","version":"1"}
{"action":{"identity":{"address":"N\u0000sourcecred\u0000core\u0000IDENTITY\u0000HdwuQadTjb859vE3QXRWIw\u0000","aliases":[],"id":"HdwuQadTjb859vE3QXRWIw","name":"beanow-sc-test","subtype":"USER"},"type":"CREATE_IDENTITY"},"ledgerTimestamp":1704154647781,"uuid":"6rwCvWem7jykpC5lhnl26w","version":"1"}
{"action":{"alias":{"address":"N\u0000sourcecred\u0000discourse\u0000user\u0000https://sourcecred-test.discourse.group\u0000beanow.sc-test\u0000","description":"discourse/[@beanow.sc-test](https://sourcecred-test.discourse.group/u/beanow.sc-test/)"},"identityId":"HdwuQadTjb859vE3QXRWIw","type":"ADD_ALIAS"},"ledgerTimestamp":1704154647781,"uuid":"jlSb3e2EZ2qbOBc7rJ14wA","version":"1"}
{"action":{"identity":{"address":"N\u0000sourcecred\u0000core\u0000IDENTITY\u0000fQvJONxAM3E2mQl8IaRiXg\u0000","aliases":[],"id":"fQvJONxAM3E2mQl8IaRiXg","name":"SourceCred","subtype":"PROJECT"},"type":"CREATE_IDENTITY"},"ledgerTimestamp":1704154647828,"uuid":"NYmvgodqOZfE98DGxRqmVw","version":"1"}
{"action":{"identityId":"fQvJONxAM3E2mQl8IaRiXg","type":"TOGGLE_ACTIVATION"},"ledgerTimestamp":1704154647828,"uuid":"L10iokTByO1pIMmcyv5Fxg","version":"1"}
